setup.cfg
setup.py
popo_attribute_tracker/__init__.py
popo_attribute_tracker/attribute_tracker.py
popo_attribute_tracker/test_attribute_tracker.py
popo_attribute_tracker.egg-info/PKG-INFO
popo_attribute_tracker.egg-info/SOURCES.txt
popo_attribute_tracker.egg-info/dependency_links.txt
popo_attribute_tracker.egg-info/not-zip-safe
popo_attribute_tracker.egg-info/top_level.txt