Metadata-Version: 1.0
Name: popo-attribute-tracker
Version: 0.1
Summary: Simple Attribute Tracker for POPOs
Home-page: https://github.com/farfanoide/popo_attribute_tracker
Author: Ivan Karl
Author-email: ivan6258@gmail.com
License: MIT
Platform: UNKNOWN
